{"terms": {"this": {"0": [0], "2": [1, 2, 5], "3": [32, 45, 47], "5": [91, 101, 110, 116, 177], "6": [199, 208]}, "is": {"0": [0], "2": [1, 26], "3": [32, 45, 47, 64, 72], "5": [81, 87, 95, 100, 101, 104, 110, 113, 116, 151, 153, 177, 189], "6": [190, 199, 200, 202, 205, 208, 210]}, "an": {"0": [0], "2": [2, 4], "5": [81, 100, 104, 106, 115, 116, 124], "6": [199, 208]}, "encyclopedia": {"0": [0]}, "of": {"0": [0], "2": [1, 6], "3": [31, 32, 44, 45, 47, 62, 72], "4": [79], "5": [81, 87, 91, 93, 98, 100, 101, 104, 106, 108, 110, 113, 115, 116, 119, 124, 126, 128, 130, 136, 142, 151, 185, 186, 187, 189], "6": [190, 197, 199, 200, 202, 203, 208]}, "knowledge": {"0": [0]}, "tinellb": {"0": [0], "2": [1], "6": [190, 197, 205]}, "within": {"2": [1], "5": [176, 179], "6": [190, 199, 202, 203]}, "the": {"2": [1, 2, 3, 4, 5, 6], "3": [32, 44, 45, 47, 49, 55, 57, 62, 64, 70, 72], "4": [79], "5": [81, 87, 89, 91, 93, 95, 98, 100, 101, 103, 104, 106, 108, 110, 113, 115, 116, 119, 124, 126, 128, 136, 142, 145, 151, 153, 163, 174, 176, 177, 185, 186, 187, 189], "6": [190, 199, 200, 203, 208, 209]}, "universe": {"2": [1, 3, 26], "5": [81], "6": [190]}, "named": {"2": [1, 2]}, "there": {"2": [1], "5": [81, 103, 110], "6": [199, 200, 202, 205, 207]}, "a": {"2": [1, 3], "3": [32, 45, 47, 64, 72], "5": [81, 100, 101, 104, 106, 108, 110, 113, 115, 116, 119, 124, 126, 128, 163, 174, 176, 177, 186, 187], "6": [190, 199, 200, 207, 208, 209]}, "planet": {"2": [1], "6": [199]}, "ptoko": {"2": [1, 5, 26]}, "arose": {"2": [1]}, "on": {"2": [1, 4, 5], "3": [45, 47], "5": [98, 100, 101, 110, 187], "6": [205, 209]}, "world": {"2": [1, 2, 3, 4], "3": [49]}, "race": {"2": [1]}, "humanoids": {"2": [1]}, "ptokan": {"2": [1, 5, 11, 12, 13]}, "over": {"2": [1], "5": [186]}, "millions": {"2": [1]}, "years": {"2": [1]}, "their": {"2": [1, 2, 3, 5], "3": [32, 44, 45, 70], "5": [89, 93, 104, 115, 119], "6": [200]}, "evolved": {"2": [1, 4, 5]}, "and": {"2": [1, 4, 5], "3": [32, 44, 45, 47, 72], "5": [91, 93, 98, 103, 104, 110, 112, 114, 116, 119, 124, 136, 142, 145, 153, 155, 163, 174, 176, 177, 179, 185, 187, 189], "6": [199, 202, 205, 207]}, "became": {"2": [1]}, "dominant": {"2": [1], "5": [189]}, "force": {"2": [1], "5": [104, 106, 107, 108, 109, 110, 119, 126, 128, 153, 176, 187, 189]}, "had": {"2": [1]}, "been": {"2": [1]}, "many": {"2": [1], "6": [197]}, "conflicts": {"2": [1]}, "small": {"2": [1], "5": [97, 132, 133, 143, 155, 156], "6": [200]}, "large": {"2": [1], "5": [132, 133, 143, 155, 156, 188], "6": [205]}, "throughout": {"2": [1]}, "history": {"2": [1]}, "one": {"2": [1, 3, 4], "3": [45], "5": [116, 176, 189], "6": [199, 200, 202, 203]}, "particularly": {"2": [1]}, "bloody": {"2": [1]}, "war": {"2": [1, 3]}, "much": {"2": [1], "5": [89]}, "population": {"2": [1]}, "brought": {"2": [1]}, "into": {"2": [1, 3, 5], "3": [47]}, "it": {"2": [1], "3": [32, 49], "5": [91, 101, 106, 108, 153, 189]}, "survivors": {"2": [1]}, "were": {"2": [1, 4], "6": [200]}, "ruled": {"2": [1]}, "by": {"2": [1, 3, 4, 5], "4": [79], "5": [95, 103, 185], "6": [203, 209]}, "single": {"2": [1]}, "monarch": {"2": [1]}, "generations": {"2": [2], "5": [117]}, "passed": {"2": [2]}, "people": {"2": [2, 5]}, "rebuilt": {"2": [2]}, "shattered": {"2": [2]}, "newest": {"2": [2]}, "ruler": {"2": [2]}, "queen": {"2": [2]}, "loren": {"2": [2]}, "decided": {"2": [2]}, "to": {"2": [2], "3": [32, 45, 49, 64], "4": [79], "5": [91, 93, 101, 104, 110, 176], "6": [190, 200, 203, 207, 209]}, "create": {"2": [2]}, "international": {"2": [2]}, "language": {"2": [2, 3]}, "promote": {"2": [2]}, "peace": {"2": [2, 5]}, "amongst": {"2": [2]}, "her": {"2": [2]}, "subjects": {"2": [2]}, "she": {"2": [2]}, "lulani": {"2": [2, 4, 5, 8, 9]}, "after": {"2": [2]}, "herself": {"2": [2]}, "despite": {"2": [3]}, "shared": {"2": [3]}, "as": {"2": [3], "3": [32, 47], "5": [89, 91, 101, 110, 116, 176, 179, 189], "6": [200]}, "more": {"2": [3], "3": [32]}, "time": {"2": [3, 5], "5": [189], "6": [194, 201, 202, 203]}, "went": {"2": [3]}, "fractures": {"2": [3]}, "again": {"2": [3]}, "showed": {"2": [3]}, "between": {"2": [3], "5": [93], "6": [199, 200]}, "nations": {"2": [3]}, "another": {"2": [3], "6": [200]}, "ensued": {"2": [3]}, "great": {"2": [3]}, "weapon": {"2": [3]}, "was": {"2": [3, 4, 5, 6]}, "created": {"2": [3]}, "that": {"2": [3, 5], "3": [45, 64, 72], "5": [81, 103, 110, 189], "6": [190, 200]}, "tore": {"2": [3]}, "apart": {"2": [3]}, "space‑time": {"2": [3]}, "flinging": {"2": [3]}, "its": {"2": [3], "3": [49], "5": [81, 100, 153, 177]}, "victims": {"2": [3]}, "far": {"2": [3]}, "out": {"2": [3], "3": [47]}, "such": {"2": [4], "5": [186], "6": [200]}, "group": {"2": [4]}, "fezhlê": {"2": [4, 11, 12, 13]}, "they": {"2": [4], "4": [79], "5": [98, 101, 103, 104, 110, 115, 176, 179], "6": [199, 205, 207]}, "found": {"2": [4], "5": [179, 187, 189], "6": [199]}, "themselves": {"2": [4], "5": [98]}, "empty": {"2": [4]}, "tongue": {"2": [4]}, "independently": {"2": [4]}, "from": {"2": [4], "3": [45], "5": [100], "6": [205]}, "later": {"2": [4]}, "heavily": {"2": [4], "5": [110]}, "influenced": {"2": [4]}, "zhaladi": {"2": [4, 20, 21]}, "dialects": {"2": [4]}, "remained": {"2": [5]}, "slowly": {"2": [5]}, "grew": {"2": [5]}, "back": {"2": [5]}, "towards": {"2": [5]}, "vernacular": {"2": [5]}, "thence": {"2": [5]}, "brequèn": {"2": [5, 6, 16, 17]}, "used": {"2": [5], "4": [79], "5": [163, 174]}, "only": {"2": [5], "4": [79], "5": [87, 100, 101, 103, 104, 119, 179, 189], "6": [199]}, "for": {"2": [5], "3": [47, 70], "5": [104, 115, 153, 177, 187], "6": [199, 210]}, "science": {"2": [5]}, "arts": {"2": [5]}, "not": {"2": [5], "5": [91, 110, 113, 189], "6": [203]}, "everyday": {"2": [5]}, "use": {"2": [5], "3": [70], "6": [203]}, "spoken": {"2": [6]}, "in": {"2": [6, 26], "3": [32, 45, 47, 57, 64], "4": [79], "5": [89, 110, 116, 187], "6": [190, 197, 199, 205]}, "realm": {"2": [6], "3": [47]}, "brequé": {"2": [6, 28]}, "tsarin": {"2": [6, 19, 20]}, "tsarein": {"2": [6, 30]}, "c3": {"2": [8, 9, 11, 12, 13, 15, 16, 17, 19, 20, 21], "3": [69], "5": [141]}, "high": {"2": [8], "5": [187]}, "demotic": {"2": [9]}, "c7": {"2": [10, 14, 18]}, "c2": {"2": [11, 12, 13, 19, 20, 22, 23, 24, 25], "3": [66, 67], "5": [131, 133, 140]}, "early": {"2": [11]}, "old": {"2": [11]}, "late": {"2": [12]}, "middle": {"2": [12], "5": [187]}, "koine": {"2": [13]}, "new": {"2": [13]}, "pre‑brequèn": {"2": [15]}, "archaic": {"2": [16]}, "common": {"2": [17]}, "proto‑zhaladi": {"2": [19]}, "classical": {"2": [19]}, "contemporary": {"2": [20]}, "modern": {"2": [20]}, "reformed": {"2": [21]}, "c5": {"2": [22, 23, 24, 25]}, "ancient": {"2": [22]}, "solajin": {"2": [22, 23, 24, 25]}, "medieval": {"2": [23]}, "traditional": {"2": [24]}, "standard": {"2": [25], "5": [187]}, "located": {"2": [26]}, "m204ν": {"2": [26]}, "solaji": {"2": [27], "6": [199]}, "f996ξ": {"2": [27], "6": [199]}, "d578η": {"2": [28]}, "zhalad": {"2": [29]}, "a376γ": {"2": [29]}, "e415χ": {"2": [30]}, "planes": {"3": [31, 44]}, "existence": {"3": [31, 32, 44]}, "at": {"3": [32], "5": [96, 187, 189], "6": [205]}, "fundamental": {"3": [32], "5": [80, 81, 91]}, "level": {"3": [32, 45, 47]}, "nothing": {"3": [32]}, "than": {"3": [32, 45], "5": [187]}, "movement": {"3": [32, 47], "5": [100], "6": [199, 202, 203, 205, 210]}, "darill": {"3": [32, 43, 47], "5": [84, 87, 90, 91, 98, 100, 101, 103, 110, 119, 124, 126, 128, 136, 142, 186, 187, 189]}, "acting": {"3": [32]}, "under": {"3": [32], "5": [101, 110, 187]}, "own": {"3": [32], "5": [115, 119, 153]}, "rules": {"3": [32], "6": [203]}, "seen": {"3": [32]}, "medium": {"3": [32, 50], "5": [99]}, "scale": {"3": [32], "5": [97, 98, 99, 101, 187, 188]}, "section": {"3": [32]}, "particle": {"3": [32], "5": [81, 91, 113, 115]}, "physics": {"3": [32]}, "chapter": {"3": [32]}, "though": {"3": [32]}, "can": {"3": [32], "4": [79], "5": [100, 101, 104, 110, 177, 186, 187, 189], "6": [199, 203]}, "still": {"3": [32]}, "be": {"3": [32, 64], "4": [79], "5": [91, 100, 101, 110, 115, 179, 189], "6": [200, 203]}, "useful": {"3": [32], "5": [101]}, "abstract": {"3": [32]}, "develop": {"3": [32]}, "models": {"3": [32]}, "explain": {"3": [32]}, "soul": {"3": [33, 71, 72]}, "spiritual": {"3": [33]}, "plane": {"3": [33, 35, 37, 39, 41, 47]}, "↑": {"3": [34, 36, 38, 40], "5": [101, 121]}, "heart": {"3": [35, 63, 64]}, "emotional": {"3": [35]}, "mind": {"3": [37, 56, 57]}, "mental": {"3": [37]}, "subtle": {"3": [38, 45]}, "overt": {"3": [38, 45]}, "↓": {"3": [38], "5": [101, 121]}, "body": {"3": [39, 45, 47, 48, 49]}, "physical": {"3": [39, 45, 49]}, "self": {"3": [41, 45, 46, 47]}, "fifth": {"3": [41, 47]}, "⇡": {"3": [42]}, "five": {"3": [44]}, "bodies": {"3": [44, 45]}, "associated": {"3": [44]}, "model": {"3": [45], "5": [101]}, "each": {"3": [45], "5": [101, 103, 163, 174, 185], "6": [197, 200, 205]}, "emergent": {"3": [45], "5": [100]}, "below": {"3": [45]}, "sufficiently": {"3": [45]}, "complex": {"3": [45], "5": [101, 106, 108]}, "structure": {"3": [45], "5": [100]}, "gives": {"3": [45], "5": [89, 93, 177]}, "rise": {"3": [45]}, "phenomena": {"3": [45]}, "higher": {"3": [45]}, "are": {"3": [45], "4": [79], "5": [81, 91, 93, 98, 103, 110, 115, 119, 163, 174, 179, 186, 187, 189], "6": [199, 200, 202, 205, 207]}, "greater": {"3": [45]}, "sum": {"3": [45]}, "parts": {"3": [45]}, "consist": {"3": [45], "5": [124, 130]}, "all": {"3": [45], "5": [91], "6": [190]}, "other": {"3": [45], "4": [79], "5": [93, 115, 116], "6": [200, 205]}, "also": {"3": [47, 72], "4": [79], "5": [110, 151]}, "known": {"3": [47]}, "energy": {"3": [47], "5": [151, 187]}, "or": {"3": [47, 70], "4": [79], "5": [101, 115, 126, 128, 189], "6": [199, 200, 203]}, "which": {"3": [47, 64], "5": [101, 110, 163, 174, 187], "6": [190, 199, 205]}, "binds": {"3": [47]}, "form": {"3": [47], "5": [91, 103, 119, 126, 128], "6": [190]}, "quasi‑particles": {"3": [47]}, "called": {"3": [47], "5": [81, 151, 189]}, "allows": {"3": [47], "5": [177, 187]}, "matter": {"3": [47], "5": [114, 116, 189]}, "lifeform": {"3": [47]}, "uses": {"3": [49]}, "senses": {"3": [49, 55]}, "perceive": {"3": [49]}, "information": {"3": [49]}, "about": {"3": [49], "5": [189]}, "around": {"3": [49]}, "h": {"3": [50, 65], "5": [82, 83, 121, 122, 123, 131, 137, 146, 147, 148, 149, 150, 158, 159, 160, 161, 162, 165, 181], "6": [192]}, "sense": {"3": [50]}, "chemical": {"3": [51]}, "taste": {"3": [51]}, "smell": {"3": [51]}, "radiation": {"3": [52]}, "sight": {"3": [52]}, "vibration": {"3": [53]}, "hearing": {"3": [53]}, "contact": {"3": [54]}, "touch": {"3": [54]}, "four": {"3": [55, 62, 70], "5": [81, 87], "6": [207]}, "main": {"3": [55, 62, 70], "5": [91]}, "thought": {"3": [57, 62]}, "occurs": {"3": [57]}, "etiquette": {"3": [58]}, "intuition": {"3": [59]}, "rationality": {"3": [60]}, "instinct": {"3": [61]}, "modes": {"3": [62]}, "feels": {"3": [64]}, "emotions": {"3": [64, 70]}, "balance": {"3": [64]}, "said": {"3": [64]}, "happy": {"3": [64]}, "negative": {"3": [65, 70], "5": [101, 176]}, "neutral": {"3": [65]}, "positive": {"3": [65, 70], "5": [101, 176]}, "sadness": {"3": [66]}, "melancholy": {"3": [66]}, "anger": {"3": [67]}, "passion": {"3": [67]}, "complacence": {"3": [68]}, "contentment": {"3": [68]}, "joy": {"3": [68]}, "fear": {"3": [69]}, "some": {"3": [70], "5": [110], "6": [210]}, "different": {"3": [70], "5": [93, 96, 128, 151]}, "terms": {"3": [70]}, "aspects": {"3": [70]}, "part": {"3": [72]}, "person": {"3": [72]}, "loves": {"3": [72]}, "source": {"3": [72]}, "morality": {"3": [72]}, "compassion": {"3": [73]}, "affection": {"3": [74]}, "fondness": {"3": [75]}, "attraction": {"3": [76]}, "foundation": {"4": [77]}, "concepts": {"4": [77]}, "wormholes": {"4": [78, 79], "6": [203]}, "connect": {"4": [79]}, "two": {"4": [79], "5": [113, 115, 130, 176, 185], "6": [200, 202]}, "points": {"4": [79]}, "spacetime": {"4": [79]}, "method": {"4": [79]}, "jumping": {"4": [79]}, "times": {"4": [79]}, "realities": {"4": [79], "6": [199, 200]}, "circumvent": {"4": [79]}, "limits": {"4": [79]}, "imposed": {"4": [79]}, "speed": {"4": [79]}, "light": {"4": [79]}, "fields": {"5": [80, 81, 87]}, "fill": {"5": [81]}, "excitation": {"5": [81]}, "field": {"5": [81, 82, 87, 89, 92, 93]}, "spin": {"5": [81, 82, 85, 87, 89, 92, 93, 113, 136, 142, 145, 155]}, "measure": {"5": [81]}, "intrinsic": {"5": [81, 101, 104, 106, 108, 110]}, "angular": {"5": [81, 89]}, "momentum": {"5": [81, 89]}, "symbol": {"5": [82, 146, 157, 164]}, "higgs": {"5": [83, 88, 89]}, "0": {"5": [83, 113, 145, 176, 179]}, "д": {"5": [84]}, "½": {"5": [84, 113, 136, 142, 145, 155]}, "ƨ": {"5": [85]}, "1": {"5": [85, 113, 136, 142, 147, 159, 166], "6": [193, 199]}, "gravity": {"5": [86, 94, 95, 98, 119, 189]}, "g": {"5": [86, 134, 140, 143]}, "2": {"5": [86, 113, 148, 160, 168], "6": [194]}, "elementary": {"5": [87]}, "three": {"5": [87, 103, 124, 126, 128], "6": [205]}, "these": {"5": [87, 103, 119, 124, 186, 187, 189]}, "have": {"5": [87, 101, 104, 115, 116, 136, 142, 145, 155, 176, 179]}, "integer": {"5": [87, 104, 113]}, "with": {"5": [87, 98, 100, 103, 106, 108, 113, 115, 116, 119, 126, 128, 189], "6": [199]}, "half-integer": {"5": [87, 113]}, "particles": {"5": [89, 91, 93, 100, 101, 104, 111, 115, 116, 124, 126, 128, 136, 142, 186]}, "mass": {"5": [89, 115, 136, 142, 153, 177]}, "same": {"5": [89, 100, 113, 126]}, "way": {"5": [89, 100]}, "imparts": {"5": [89]}, "would": {"5": [91], "6": [200]}, "altogether": {"5": [91]}, "inaccurate": {"5": [91]}, "consider": {"5": [91]}, "non-fundamental": {"5": [91]}, "topic": {"5": [91]}, "work": {"5": [91, 110], "6": [199]}, "values": {"5": [93, 104]}, "due": {"5": [93]}, "coupling": {"5": [93]}, "strengths": {"5": [93]}, "any": {"5": [93, 101, 189], "6": [205]}, "given": {"5": [93, 104], "6": [190]}, "mediated": {"5": [95, 103]}, "graviton": {"5": [95]}, "behaviour": {"5": [96, 98, 101]}, "scales": {"5": [96, 189], "6": [205]}, "dynamics": {"5": [98]}, "individual": {"5": [98]}, "poorly": {"5": [98]}, "understood": {"5": [98]}, "smallest": {"5": [98]}, "display": {"5": [98]}, "chaotic": {"5": [98], "6": [210]}, "interacting": {"5": [98]}, "what": {"5": [100]}, "we": {"5": [100]}, "call": {"5": [100]}, "reality": {"5": [100], "6": [193, 198, 199]}, "phenomenon": {"5": [100]}, "analogy": {"5": [100]}, "drawn": {"5": [100]}, "water": {"5": [100]}, "waves": {"5": [100]}, "ocean": {"5": [100]}, "wave": {"5": [100]}, "made": {"5": [100]}, "but": {"5": [100, 113, 177, 187]}, "itself": {"5": [100]}, "comes": {"5": [100]}, "bulk": {"5": [100], "6": [190]}, "move": {"5": [100, 104]}, "across": {"5": [100], "6": [205]}, "entire": {"5": [100]}, "pacific": {"5": [100]}, "component": {"5": [100]}, "molecules": {"5": [100]}, "short": {"5": [100, 186]}, "distance": {"5": [100]}, "act": {"5": [100, 176]}, "collective": {"5": [101]}, "treated": {"5": [101]}, "if": {"5": [101, 104, 115], "6": [200]}, "formed": {"5": [101, 124, 136, 142, 185]}, "quasi-": {"5": [101]}, "complices": {"5": [101]}, "singular": {"5": [101, 104]}, "specific": {"5": [101]}, "will": {"5": [101, 115], "6": [202, 203]}, "involved": {"5": [101, 110]}, "momentarily": {"5": [101]}, "however": {"5": [101], "6": [203, 207, 210]}, "containing": {"5": [101]}, "certain": {"5": [101]}, "number": {"5": [101, 110], "6": [192, 199, 200]}, "valence": {"5": [101]}, "+1": {"5": [101, 115]}, "-1": {"5": [101, 115]}, "charge": {"5": [101, 104, 106, 108, 110, 115, 126, 145, 153, 155, 176, 179]}, "manifests": {"5": [101]}, "induced": {"5": [101, 104, 110]}, "circumstances": {"5": [101, 110]}, "interactions": {"5": [102, 103, 187]}, "couple": {"5": [103]}, "when": {"5": [103, 106, 108]}, "complexes": {"5": [103]}, "electromagnetic": {"5": [103, 104, 106, 126, 153, 189]}, "strong": {"5": [103, 104, 107, 108, 128, 176, 189]}, "weak": {"5": [103, 109, 110, 119, 187]}, "forces": {"5": [103, 104, 189]}, "quasiparticles": {"5": [103, 189]}, "product": {"5": [104]}, "constant": {"5": [104]}, "freely": {"5": [104, 179]}, "equal": {"5": [104]}, "multiple": {"5": [104]}, "quanta": {"5": [104]}, "quantum": {"5": [104]}, "electromagnetism": {"5": [105]}, "interacts": {"5": [106, 108, 189]}, "induces": {"5": [106, 108]}, "electric": {"5": [106, 145, 155, 176, 179]}, "⅙": {"5": [106]}, "color": {"5": [108, 145, 155, 176, 179]}, "⅓": {"5": [108]}, "rearranging": {"5": [110]}, "types": {"5": [110]}, "interaction": {"5": [110]}, "even": {"5": [110]}, "non-valence": {"5": [110]}, "dependent": {"5": [110]}, "easily": {"5": [110]}, "calculated": {"5": [110]}, "necessarily": {"5": [110]}, "proportional": {"5": [110]}, "mechanics": {"5": [110]}, "thereby": {"5": [110]}, "beyond": {"5": [110], "6": [200]}, "scope": {"5": [110]}, "fermions": {"5": [112, 113]}, "bosons": {"5": [112, 113, 180, 185, 187]}, "boson": {"5": [113]}, "while": {"5": [113]}, "3": {"5": [113, 149, 161, 170, 182, 184], "6": [195]}, "5": {"5": [113]}, "fermion": {"5": [113]}, "cannot": {"5": [113, 179]}, "occupy": {"5": [113]}, "state": {"5": [113, 177]}, "true": {"5": [113]}, "antimatter": {"5": [114, 116]}, "identical": {"5": [115]}, "properties": {"5": [115]}, "opposite": {"5": [115]}, "sign": {"5": [115]}, "antiparticles": {"5": [115]}, "instance": {"5": [115]}, "antiparticle": {"5": [115, 119, 153]}, "uncharged": {"5": [115]}, "may": {"5": [115]}, "particle-antiparticle": {"5": [116]}, "pair": {"5": [116, 119, 186]}, "arbitrarily": {"5": [116]}, "labelled": {"5": [116], "6": [199]}, "document": {"5": [116]}, "prefix": {"5": [116]}, "anti-": {"5": [116, 151]}, "appear": {"5": [116]}, "overline": {"5": [116]}, "◌": {"5": [116]}, "doublets": {"5": [118]}, "neutrino": {"5": [119, 124, 177]}, "ν": {"5": [119]}, "interact": {"5": [119, 126, 128, 189]}, "neutrinos": {"5": [119]}, "massless": {"5": [119]}, "triplets": {"5": [120, 130]}, "hc2": {"5": [121, 157, 164]}, "↑↑": {"5": [122]}, "halvon": {"5": [122, 126]}, "ч": {"5": [122, 123, 131, 132, 133, 137, 138, 139]}, "grain": {"5": [122, 128, 186]}, "з": {"5": [122, 123, 131, 134, 135, 137, 140, 141]}, "↓↓": {"5": [123]}, "antihalvon": {"5": [123]}, "antigrain": {"5": [123]}, "base": {"5": [124]}, "additional": {"5": [124]}, "halvons": {"5": [125, 176, 185]}, "↑↑↑": {"5": [126]}, "↓↓↓": {"5": [126]}, "involving": {"5": [126, 128]}, "grains": {"5": [127, 185]}, "charges": {"5": [128]}, "↑↑↓": {"5": [128]}, "↓↓↑": {"5": [128]}, "hextuples": {"5": [129, 130]}, "charged": {"5": [132, 133, 143, 144, 145, 151]}, "antilepton": {"5": [132]}, "ℓ": {"5": [132, 133, 138, 139, 143]}, "photon": {"5": [132, 136, 142, 143, 153]}, "γ": {"5": [132, 138, 143]}, "quark": {"5": [132, 133, 143, 163, 174]}, "q": {"5": [132, 133, 138, 139, 143]}, "antiquark": {"5": [132, 133]}, "lepton": {"5": [133, 143, 151]}, "c4": {"5": [134]}, "bigrain": {"5": [134, 143]}, "ф": {"5": [134, 135, 140, 141, 143]}, "gluon": {"5": [134, 136, 142, 143, 177]}, "c6": {"5": [135]}, "antibigrain": {"5": [135]}, "lowest": {"5": [136, 142]}, "six": {"5": [136, 142]}, "rest": {"5": [136, 142, 189]}, "c1": {"5": [139]}, "key": {"5": [143]}, "—": {"5": [143]}, "leptons": {"5": [144, 145, 187]}, "±1": {"5": [145]}, "generation": {"5": [146, 156, 164]}, "name": {"5": [146, 157, 163, 164, 174], "6": [190]}, "electron": {"5": [147]}, "e": {"5": [147, 151], "6": [190]}, "muon": {"5": [148]}, "μ": {"5": [148]}, "tau": {"5": [149]}, "τ": {"5": [149]}, "4": {"5": [150, 162, 172], "6": [196]}, "yaon": {"5": [150]}, "я": {"5": [150]}, "states": {"5": [151]}, "antielectron": {"5": [151]}, "positron": {"5": [151]}, "photons": {"5": [152]}, "has": {"5": [153, 163, 174]}, "no": {"5": [153], "6": [200]}, "carrier": {"5": [153]}, "quarks": {"5": [154, 155, 156, 163, 174, 187]}, "±⅓": {"5": [155]}, "±⅔": {"5": [155]}, "hr3": {"5": [156]}, "hc3": {"5": [156]}, "hr2": {"5": [157, 164, 166, 168, 170, 172]}, "prosaic": {"5": [158, 163, 165, 174]}, "poetic": {"5": [158, 163, 165, 174]}, "up": {"5": [159, 166]}, "unique": {"5": [159, 166]}, "u": {"5": [159, 166]}, "down": {"5": [159, 167]}, "dream": {"5": [159, 167]}, "d": {"5": [159, 167]}, "centre": {"5": [160, 168]}, "charm": {"5": [160, 168]}, "c": {"5": [160, 168]}, "spiral": {"5": [160, 169]}, "strange": {"5": [160, 169]}, "s": {"5": [160, 169]}, "top": {"5": [161, 170]}, "truth": {"5": [161, 170]}, "t": {"5": [161, 170]}, "bottom": {"5": [161, 171]}, "beauty": {"5": [161, 171]}, "b": {"5": [161, 171]}, "left": {"5": [162, 172]}, "love": {"5": [162, 172]}, "l": {"5": [162, 172]}, "right": {"5": [162, 173]}, "rhyme": {"5": [162, 173]}, "r": {"5": [162, 173]}, "both": {"5": [163, 174]}, "interchangeably": {"5": [163, 174]}, "gluons": {"5": [175, 176]}, "overall": {"5": [176]}, "nucleon": {"5": [176]}, "carry": {"5": [176]}, "tend": {"5": [176]}, "separate": {"5": [176]}, "free-moving": {"5": [177]}, "spontaneously": {"5": [177, 186]}, "become": {"5": [177, 186, 187]}, "short-lived": {"5": [177]}, "apparent": {"5": [177]}, "oscillation": {"5": [177]}, "bigrains": {"5": [178, 179]}, "∓⅓": {"5": [179]}, "non-integer": {"5": [179]}, "moving": {"5": [179]}, "thus": {"5": [179]}, "nucleons": {"5": [179]}, "massive": {"5": [180, 185]}, "gauge": {"5": [180, 185]}, "чч": {"5": [181]}, "зз": {"5": [182, 183, 184]}, "x+4": {"5": [182]}, "y+⅓": {"5": [182]}, "v-⅔": {"5": [182]}, "w+1": {"5": [183]}, "z0": {"5": [183]}, "w-1": {"5": [183]}, "v+⅔": {"5": [184]}, "y-⅓": {"5": [184]}, "x-4": {"5": [184]}, "combination": {"5": [185]}, "very": {"5": [186]}, "unstable": {"5": [186]}, "lifetime": {"5": [186]}, "free": {"5": [186], "6": [205]}, "mediate": {"5": [187]}, "shuffling": {"5": [187]}, "row": {"5": [187]}, "lighter": {"5": [187]}, "others": {"5": [187]}, "flavour-changing": {"5": [187]}, "heaviest": {"5": [187]}, "virtually": {"5": [187]}, "never": {"5": [187]}, "conditions": {"5": [187]}, "enough": {"5": [187]}, "vice": {"5": [187]}, "versa": {"5": [187]}, "15%": {"5": [189]}, "forming": {"5": [189]}, "do": {"5": [189]}, "via": {"5": [189], "6": [199]}, "so": {"5": [189]}, "dark": {"5": [189]}, "long-range": {"5": [189]}, "sea": {"5": [189]}, "i": {"6": [190]}, "exists": {"6": [190]}, "likely": {"6": [190]}, "infinite": {"6": [190]}, "extent": {"6": [190, 205]}, "particular": {"6": [190, 200]}, "bubble": {"6": [190]}, "takes": {"6": [190]}, "10‑dimensional": {"6": [190]}, "ellipsoid": {"6": [190]}, "dimensions": {"6": [191, 202, 205, 207, 209]}, "dimension": {"6": [192, 197, 199]}, "space": {"6": [195, 204, 207]}, "gingla": {"6": [196, 206, 210]}, "how": {"6": [197]}, "exist": {"6": [197]}, "relative": {"6": [199]}, "measures": {"6": [199]}, "separation": {"6": [199]}, "parallel": {"6": [199]}, "worlds": {"6": [199]}, "along": {"6": [199]}, "occur": {"6": [199]}, "wormhole": {"6": [199]}, "approximately": {"6": [199, 205]}, "million": {"6": [199, 205]}, "alphanumeric": {"6": [199]}, "code": {"6": [199]}, "consisting": {"6": [199]}, "uppercase": {"6": [199]}, "latin": {"6": [199]}, "character": {"6": [199]}, "three‑": {"6": [199]}, "four‑digit": {"6": [199]}, "lowercase": {"6": [199]}, "greek": {"6": [199]}, "letter": {"6": [199]}, "example": {"6": [199]}, "actual": {"6": [200]}, "compared": {"6": [200]}, "possible": {"6": [200, 210]}, "basically": {"6": [200]}, "zero": {"6": [200]}, "chance": {"6": [200]}, "finding": {"6": [200]}, "planets": {"6": [200]}, "complete": {"6": [200]}, "partial": {"6": [200]}, "copies": {"6": [200]}, "being": {"6": [200]}, "meet": {"6": [200]}, "similar": {"6": [200, 207]}, "themself": {"6": [200]}, "connection": {"6": [200]}, "them": {"6": [200]}, "similarity": {"6": [200]}, "temporal": {"6": [202]}, "subjective": {"6": [202, 203]}, "objective": {"6": [202, 203]}, "through": {"6": [202, 203, 210]}, "either": {"6": [202]}, "usually": {"6": [202]}, "involuntary": {"6": [202, 210]}, "continuous": {"6": [202, 205, 207]}, "unidirectional": {"6": [202]}, "always": {"6": [202, 203]}, "grow": {"6": [202, 203]}, "older": {"6": [202, 203]}, "one’s": {"6": [202, 203]}, "frame": {"6": [202, 203]}, "reference": {"6": [202, 203]}, "altered": {"6": [203]}, "according": {"6": [203]}, "special": {"6": [203]}, "relativity": {"6": [203]}, "navigated": {"6": [203]}, "spatial": {"6": [205]}, "indistinguishable": {"6": [205]}, "allow": {"6": [205]}, "direction": {"6": [205]}, "macroscopic": {"6": [205]}, "topologically": {"6": [205]}, "flat": {"6": [205]}, "greatest": {"6": [205]}, "20": {"6": [205]}, "lightyears": {"6": [205]}, "ginglaic": {"6": [207, 209]}, "similarly": {"6": [207]}, "microscopic": {"6": [207]}, "bundled": {"6": [207, 209]}, "together": {"6": [207]}, "calabi–yau": {"6": [207, 208]}, "manifold": {"6": [207, 209]}, "image": {"6": [208, 209]}, "two-dimensional": {"6": [208]}, "hypersurface": {"6": [208]}, "quintic": {"6": [208]}, "three-fold": {"6": [208]}, "represented": {"6": [209]}, "here": {"6": [209]}, "calabi‑yau": {"6": [209]}, "attributed": {"6": [209]}, "user": {"6": [209]}, "jbourjai": {"6": [209]}, "https": {"6": [209]}, "en": {"6": [209]}, "wikipedia": {"6": [209]}, "org": {"6": [209]}, "wiki": {"6": [209]}, "file": {"6": [209]}, "calabi": {"6": [209]}, "yau": {"6": [209]}, "jpg": {"6": [209]}, "wikimedia": {"6": [209]}, "most": {"6": [210]}, "voluntary": {"6": [210]}, "individuals": {"6": [210]}}, "lines": ["This is an encyclopedia of knowledge of Tinellb.", "Within the universe named Tinellb, there is a planet named Ptoko. There arose on this world a race of humanoids, the Ptokan. Over millions of years, their race evolved and became the dominant force on their planet. There had been many conflicts, small and large, throughout their history. One particularly bloody war had had much of the population brought into it: a World War. The survivors of this war were ruled by a single monarch.", "Generations passed. The people rebuilt their shattered world. The newest ruler, Queen Loren, decided to create an international language to promote peace amongst her subjects. She named this language Lulani after herself.", "Despite their shared language, as more time went by, fractures again showed between nations. Another world war ensued. A great weapon was created, one that tore apart space‑time, flinging its victims far out into the universe.", "One such group were the Fezhlê. They found themselves on an empty world. The Fezhlê tongue evolved independently from Lulani, and was later heavily influenced by Zhaladi dialects.", "The people that remained on Ptoko slowly grew back towards peace. Their vernacular evolved into Ptokan, and thence into Brequèn. By this time, Lulani was used only for science and the arts, not for everyday use.", "Brequèn was spoken in the realm of Brequé, Tsarin in Tsarein.", "|||||", "|c3 High Lulani |c3", "|c3 Demotic Lulani |c3", "c7", "c2 Early Fezhlê ||c3 Old Ptokan |", "c2 Late Fezhlê ||c3 Middle Ptokan |", "c2 Koine Fezhlê ||c3 New Ptokan |", "c7", "c3 |c3 Pre‑Brequèn |", "c3 |c3 Archaic Brequèn |", "c3 |c3 Common Brequèn |", "c7", "|c3 Proto‑Zhaladi ||c2 Classical Tsarin", "|c3 Contemporary Zhaladi ||c2 Modern Tsarin", "|c3 Reformed Zhaladi", "c5 |c2 Ancient Solajin", "c5 |c2 Medieval Solajin", "c5 |c2 Traditional Solajin", "c5 |c2 Standard Solajin", "Ptoko is located in Universe M204ν", "Solaji: F996ξ", "Brequé: D578η", "Zhalad: A376γ", "Tsarein: E415χ", "Planes of Existence", "At a fundamental level, existence is nothing more than the movement of darill acting under their own rules. As seen in the medium scale section of the particle physics chapter, though, it can still be useful to abstract this movement, and develop models to explain it.", "Soul (spiritual plane)", "↑", "Heart (emotional plane)", "↑", "Mind (mental plane)", "↑ Subtle ↑ Overt ↓", "Body (physical plane)", "↑", "Self (fifth plane)", "⇡", "Darill", "The five bodies and their associated planes of existence. ", "In this model, each body is emergent from the one below: a sufficiently complex structure on one level gives rise to phenomena on a higher level that are greater than the sum of their parts. The overt bodies consist of the physical body and the self. All other bodies are subtle.", "Self", "The fifth plane, also known as the “energy plane”, or the “fifth plane, which binds”, is the realm in which darill form quasi‑particles. A body on this level is called a Self, and allows for movement of energy and matter into and out of the lifeform.", "Body", "The physical body uses its senses to perceive information about the world around it.", "h medium |h sense", " chemical | taste / smell", " radiation | sight", " vibration | hearing", " contact | touch", "The four main senses.", "Mind", "Thought occurs in the mind.", " etiquette", " intuition", " rationality", " instinct", "The four main modes of thought.", "Heart", "The heart is that which feels emotions. A heart in balance is said to be happy.", "h negative |h neutral |h positive", "c2 sadness | melancholy", " anger |c2 passion", " complacence | contentment | joy", "c3 fear", "The four main emotions. Some emotions use different terms for their positive or negative aspects.", "Soul", "The soul is the part of a person that loves, and is also the source of morality.", " compassion", " affection", " fondness", " attraction", "Foundation Concepts", "Wormholes", "Wormholes connect two points in spacetime. They are the only method of jumping to other times or realities. They can also be used to circumvent the limits imposed by the speed of light.", "Fundamental Fields", "There are four fundamental fields that fill the universe. An excitation of a field is called a particle. The spin of a particle is a measure of its intrinsic angular momentum.", "h field |h symbol |h spin", " Higgs | h | 0", " darill | д | ½", " spin | ƨ | 1", " gravity | g | 2", "The four elementary fields. Three of these have integer spin, the darill is the only field with half-integer spin.", "Higgs", "The Higgs field gives particles their mass in much the same way as the spin field imparts angular momentum.", "Darill", "It would not be altogether inaccurate to consider the darill as the fundamental particle. Darill form all non-fundamental particles and are the main topic of this work.", "Spin Field", "The spin field gives particles their spin. Different values of spin are due to different coupling strengths between the spin field and any other given field.", "Gravity", "Gravity is mediated by the graviton.", "Behaviour at Different Scales", "Small Scale", "The dynamics of individual darill are poorly understood. On the smallest scale, they display chaotic behaviour, interacting with gravity and with themselves.", "Medium Scale", "What we call reality is an emergent phenomenon. An analogy can be drawn with water waves on the ocean. A wave is made of particles, but the structure itself comes from bulk movement.  A wave can move across the entire Pacific; its component molecules move only a short distance. Darill act the same way.", "On this scale, the collective behaviour of darill can be treated as if they formed (quasi-)particles or complices (singular: complex). Any specific darill will only be involved momentarily. However, it is useful to model this complex as containing a certain number of valence darill. They each have a positive (+1, ↑) or negative (-1, ↓) intrinsic charge, which manifests as induced charge under specific circumstances.", "Interactions", "There are three interactions that only couple with darill when they form complexes. These are the electromagnetic, the strong and the weak forces. They are each mediated by quasiparticles.", "For the electromagnetic and strong forces, the induced charge is the product of the intrinsic charge and a given force constant. Particles can only move freely if they have values of induced charge equal to an integer multiple of their quanta (singular: quantum).", "Electromagnetism", "When the electromagnetic force interacts with a complex, it induces an electric charge of ⅙ of the intrinsic charge.", "Strong force", "When the strong force interacts with a complex, it induces a color charge of ⅓ of the intrinsic charge.", "Weak force", "The weak force is involved in rearranging darill. There are a number of types of charge that can be induced under this interaction, some of which can also be induced even in non-valence darill. They are heavily dependent on the circumstances, and are not easily calculated as they are not necessarily proportional to intrinsic charge. The mechanics of the weak force on darill are thereby beyond the scope of this work.", "Particles", "Fermions and Bosons", "A particle with integer spin (0, 1, 2…) is a boson, while a particle with half-integer spin (½, 3/2, 5/2…) is a fermion. Two fermions cannot occupy the same state, but the same is not true of bosons.", "Matter and Antimatter", "Two particles of identical mass with properties of the opposite sign are antiparticles. For instance, a particle with +1 charge will have an antiparticle with -1 charge. Uncharged particles may have antiparticles if they have other properties with opposite sign, or they may be their own antiparticles.", "Of a particle-antiparticle pair, one is arbitrarily labelled as matter, the other antimatter. In this document, antimatter particles have the prefix anti-, and appear with an overline (◌).", "Generations", "Doublets", "A pair of darill form a neutrino (ν). These only interact with gravity and the weak force. Neutrinos are massless, and are their own antiparticle.", "Triplets", "h |hc2 ↑ |hc2 ↓", "h ↑↑ | halvon | ч | grain | з", "h ↓↓ | antihalvon | ч | antigrain | з", "The particles formed of three darill. These consist of a base neutrino and an additional darill.", "Halvons", "Three darill of the same charge, (↑↑↑) or (↓↓↓), form a halvon. Particles involving a halvon interact with the electromagnetic force.", "Grains", "Three darill of different charges, (↑↑↓) or (↓↓↑), form a grain. Particles involving a grain interact with the strong force.", "Hextuples", "Hextuples consist of two triplets.", "h |c2 ч |c2 з |c2 ч |c2 з", " ч | charged antilepton | ℓ | photon | γ | large quark | q | small antiquark | q", " ч |c2 | charged lepton | ℓ | small quark | q | large antiquark | q", " з |c4 | bigrain | ф | gluon | g", " з |c6 | antibigrain | ф", "The lowest mass particles formed of six darill. The photon and the gluon have spin 1, the rest have spin ½", "h | ч | з | ч | з", " ч | ℓ | γ | q | q", " ч |c1 | ℓ | q | q", " з |c2 | ф | g", " з |c3 | ф", "The lowest mass particles formed of six darill. The photon and the gluon have spin 1, the rest have spin ½.", "|Key — ℓ: charged lepton, γ: photon, q: small quark, q: large quark, ф: bigrain, g: gluon.", "Charged Leptons", "The charged leptons have spin ½, electric charge ±1, and color charge 0.", "h Generation |h Name |h Symbol", "h 1 | electron | e", "h 2 | muon | μ", "h 3 | tau | τ", "h 4 | yaon | я", "The different energy states of the charged (anti-)lepton. The antielectron (e) is also called the positron.", "Photons", "The photon is its own antiparticle. It has no mass and no charge. It is the carrier for the electromagnetic force.", "Quarks", "Quarks have spin ½ and color charge ±⅓. Large quarks have electric charge ±⅔ and small quarks have electric charge ±⅓.", "hr3 Generation |hc3 Large Quarks |hc3 Small Quarks", "hc2 Name |hr2 Symbol |hc2 Name |hr2 Symbol", "h Prosaic |h Poetic |h Prosaic |h Poetic", "h 1 | up | unique | u | down | dream | d", "h 2 | centre | charm | c | spiral | strange | s", "h 3 | top | truth | t | bottom | beauty | b", "h 4 | left | love | l | right | rhyme | r", "The quarks. Each quark has both a prosaic and a poetic name, which are used interchangeably.", "hr2 Generation |hc2 Name |hr2 Symbol", "h Prosaic |h Poetic", "hr2 1 | up | unique | u", " down | dream | d", "hr2 2 | centre | charm | c", " spiral | strange | s", "hr2 3 | top | truth | t", " bottom | beauty | b", "hr2 4 | left | love | l", " right | rhyme | r", "The quarks. Each quark has both a prosaic and a poetic name, which are used interchangeably.", "Gluons", "Gluons have electric charge 0 and overall color charge 0. Within a nucleon they carry the strong force, and tend to act as two separate halvons, one positive and one negative.", "A free-moving neutrino can spontaneously become a gluon, but this state is short-lived. This gives the neutrino its apparent mass, and allows for neutrino oscillation.", "Bigrains", "Bigrains have electric charge 0 and color charge ∓⅓. As they have non-integer color charge, they cannot be found moving freely, and are thus only found within nucleons.", "Massive gauge bosons", "h | чч | чч | чч", " зз | x+4/3 | y+⅓ | v-⅔", " зз | w+1 | z0 | w-1", " зз | v+⅔ | y-⅓ | x-4/3", "The massive gauge bosons, each formed by the combination of two halvons and two grains.", "These are very unstable particles. Over such a short lifetime, the grain pair can spontaneously become a pair of free darill.", "These bosons mediate the weak force, which allows for shuffling of darill. The bosons on the middle row are lighter than the others, and mediate flavour-changing interactions. The heaviest bosons are virtually never found under standard conditions, but at a high enough energy scale, mediate interactions in which quarks can become leptons and vice versa.", "Large Scale", "Only about 15% of darill can be found forming quasiparticles at any one time. The rest do not interact via the electromagnetic or strong forces, and so are called “dark” matter. Gravity is the dominant force at these scales, as it is the only long-range force that interacts with the darill sea.", "The Universe, i.e.: all that exists, is likely infinite in extent. Tinellb is the name given to a particular bubble within the bulk, which takes the form of a 10‑dimensional ellipsoid.", "Dimensions", "h dimension |h number", " reality | 1", " time | 2", " space | 3", " gingla | 4", "How many of each dimension exist in Tinellb", "Reality", "There is one relative dimension, which measures the separation between parallel worlds. Movement along this dimension can only occur via wormhole. There are approximately 1 million realities. Within this work, they are labelled with an alphanumeric code consisting of an uppercase Latin character, a three‑ or four‑digit number, and a lowercase Greek letter. For example, the planet $solaji is found in reality F996ξ.", "As there are such a small number of actual realities, compared to the number of possible realities, there is basically zero chance of finding two planets that are complete or partial copies of each other. If one being were to meet another being similar to themself, there would be no particular connection between them beyond their similarity.", "Time", "There are two temporal dimensions, subjective time and objective time. Movement through either is usually involuntary, continuous and unidirectional. One will always grow older within one’s frame of reference.", "Movement through subjective time can not be altered. One will always grow older within one’s frame of reference. However, movement through objective time can be altered according to the rules of special relativity or be navigated by use of wormholes.", "Space", "There are three spatial dimensions, which are continuous and indistinguishable from each other. They allow free movement in any direction. They are macroscopic, and topologically flat on large scales. At greatest extent, Tinellb is approximately 20 million lightyears across.", "Gingla", "There are four ginglaic dimensions. They are continuous, similarly to space. However, they are microscopic, and bundled together similar to a Calabi–Yau manifold.", "This is an image of a two-dimensional hypersurface of the quintic Calabi–Yau three-fold", "The bundled ginglaic dimensions, represented here by a Calabi‑Yau manifold. Image attributed to user Jbourjai on https://en.wikipedia.org/wiki/File:Calabi_yau.jpg|Wikimedia.", "Movement through gingla is chaotic. Most movement is involuntary, however voluntary movement is possible for some individuals."], "urls": ["index.html", "entries\\index.html", "entries\\history.html", "entries\\metaphysics.html", "entries\\physics\\index.html", "entries\\physics\\particlephysics.html", "entries\\physics\\spacetime.html"], "pages": ["Tinellbian Encyclopedia", "Entries", "History", "Metaphysics", "Physics", "Particle Physics", "Spacetime"]}